README.rst
setup.py
GjertsenTweet/__init__.py
GjertsenTweet/authentication.py
GjertsenTweet/client.py
GjertsenTweet/consumer.py
GjertsenTweet/forms.py
GjertsenTweet/response.py
GjertsenTweet.egg-info/PKG-INFO
GjertsenTweet.egg-info/SOURCES.txt
GjertsenTweet.egg-info/dependency_links.txt
GjertsenTweet.egg-info/entry_points.txt
GjertsenTweet.egg-info/requires.txt
GjertsenTweet.egg-info/top_level.txt