Metadata-Version: 1.1
Name: GjertsenTweet
Version: 0.5.2
Summary: A simple twitter client for the command line
Home-page: https://github.com/fredgj/GjertsenTweet
Author: Fredrik Gjertsen
Author-email: f.gjertsen@gmail.com
License: GNU General Public License
Keywords: twitter,command-line tools
Platform: UNKNOWN
Classifier: Development Status :: 4 - Beta
Classifier: Environment :: Console
Classifier: Environment :: Console :: Curses
Classifier: Intended Audience :: End Users/Desktop
Classifier: Natural Language :: English
Classifier: Programming Language :: Python :: 2
Classifier: Programming Language :: Python :: 2.7
Classifier: Programming Language :: Python :: 2 :: Only
Classifier: Programming Language :: Python :: Implementation :: CPython
Classifier: Topic :: Communications
Classifier: Topic :: Internet
Classifier: Topic :: Internet :: WWW/HTTP :: Dynamic Content
Classifier: Topic :: Utilities
Classifier: License :: OSI Approved :: GNU General Public License v3 (GPLv3)
